MANIFEST.in
README.rst
setup.py
bases/__init__.py
bases/admin.py
bases/models.py
bases/tests.py
bases/urls.py
bases/views.py
bases/static/bases/base.js
bases/templates/bases/base.html
bases/templates/bases/base_with_nav.html
company/__init__.py
company/admin.py
company/models.py
company/serializers.py
company/tests.py
company/urls.py
company/views.py
company/static/company/company.js
company/static/company/ui-bootstrap-tpls-0.14.2.min.js
company/static/company/controller/company_lsit_ctrl.js
company/static/company/service/company_service.js
company/templates/company/companyList.html
company/templates/company/company_change.html
company/templates/company/company_edit.html
company/templates/company/index.html
djangoapps_company.egg-info/PKG-INFO
djangoapps_company.egg-info/SOURCES.txt
djangoapps_company.egg-info/dependency_links.txt
djangoapps_company.egg-info/requires.txt
djangoapps_company.egg-info/top_level.txt
usercenter/__init__.py
usercenter/admin.py
usercenter/models.py
usercenter/tests.py
usercenter/urls.py
usercenter/views.py
usercenter/static/usercenter/usercenter.js
usercenter/templates/usercenter/usercenter_changepwd.html
usercenter/templates/usercenter/usercenter_login.html
usercenter/templates/usercenter/usercenter_register.html